odc/aio.py
odc/azure.py
odc/ppt.py
odc/thredds.py
odc/aws/__init__.py
odc/aws/_find.py
odc/aws/dns.py
odc/aws/inventory.py
odc/aws/misc.py
odc/aws/queue.py
odc/aws/s3_client.py
odc/cloud/__init__.py
odc/cloud/_version.py
odc_cloud-0.2.5.dist-info/LICENSE
odc_cloud-0.2.5.dist-info/METADATA
odc_cloud-0.2.5.dist-info/WHEEL
odc_cloud-0.2.5.dist-info/top_level.txt
odc_cloud-0.2.5.dist-info/RECORD
