Metadata-Version: 2.1
Name: odc-cloud
Version: 0.2.5
Summary: Various AWS helper methods
Home-page: https://github.com/opendatacube/odc-tools/
Author: Open Data Cube
Author-email: 
Maintainer: Open Data Cube
Maintainer-email: 
License: Apache License 2.0
Platform: any
Requires-Python: >=3.9
License-File: LICENSE
Requires-Dist: botocore
Requires-Dist: boto3
Provides-Extra: async
Requires-Dist: aiobotocore[boto3] >=1.0 ; extra == 'async'
Provides-Extra: azure
Requires-Dist: azure-storage-blob ; extra == 'azure'
Provides-Extra: thredds
Requires-Dist: thredds-crawler ; extra == 'thredds'
Requires-Dist: requests ; extra == 'thredds'
